pycafe/__about__.py
pycafe/__init__.py
pycafe-0.0.1.dist-info/METADATA
pycafe-0.0.1.dist-info/WHEEL
pycafe-0.0.1.dist-info/licenses/LICENSE.txt
pycafe-0.0.1.dist-info/RECORD
